{
  "version": 6,
  "configurePresets": [
    {
      "name": "windows-os",
      "hidden": true,
      "generator": "Visual Studio 17 2022",

      "binaryDir": "${sourceDir}/build/${presetName}",
      "installDir": "${sourceDir}/build/install/${presetName}",

      "toolchainFile": "$env{VCPKG_ROOT}/scripts/buildsystems/vcpkg.cmake"
    },
    {
      "name": "mac-os",
      "hidden": true,
      "generator": "Unix Makefiles",

      "binaryDir": "${sourceDir}/build/${presetName}",
      "installDir": "${sourceDir}/build/install/${presetName}",

      "toolchainFile": "$env{VCPKG_ROOT}/scripts/buildsystems/vcpkg.cmake"
    },
    {
      "name": "win-debug",
      "inherits": "windows-os",

      "architecture": {
        "value": "x64",
        "strategy": "external"
      },

      "cacheVariables": {
        "CMAKE_BUILD_TYPE": "Debug",
        "CMAKE_CXX_COMPILER": "cl"
      }
    },
    {
      "name": "win-release",
      "inherits": "windows-os",

      "architecture": {
        "value": "x64",
        "strategy": "external"
      },

      "cacheVariables": {
        "CMAKE_BUILD_TYPE": "Release",
        "CMAKE_CXX_COMPILER": "cl"
      }
    },
    {
      "name": "mac-debug",
      "inherits": "mac-os",

      "cacheVariables": {
        "CMAKE_BUILD_TYPE": "Debug",
        "CMAKE_CXX_COMPILER": "clang++"
      }
    },
    {
      "name": "mac-release",
      "inherits": "mac-os",
      
      "cacheVariables": {
        "CMAKE_BUILD_TYPE": "Release",
        "CMAKE_CXX_COMPILER": "clang++"
      }
    }
  ],

  "buildPresets": [
    {
      "name": "Debug",
      "configurePreset": "win-debug",

      "configuration": "Debug"
    },
    {
      "name": "Release",
      "configurePreset": "win-release",

      "configuration": "Release"
    },
    {
      "name": "DebugOSX",
      "configurePreset": "mac-debug",

      "configuration": "Debug"
    },
    {
      "name": "ReleaseOSX",
      "configurePreset": "mac-release",

      "configuration": "Release"
    }
  ]
}